portablemc_console/__init__.py
portablemc_console-2.0.1.dist-info/METADATA
portablemc_console-2.0.1.dist-info/WHEEL
portablemc_console-2.0.1.dist-info/RECORD
