Metadata-Version: 2.1
Name: portablemc-console
Version: 2.0.1
Summary: Provide an interactive console for the Minecraft process' output. Also provide an API for other addons to customize the UI.
License: GPL-3.0-only
Author: Théo Rozier
Author-email: contact@theorozier.fr
Requires-Python: >=3.6.2
Classifier: License :: OSI Approved :: GNU General Public License v3 (GPLv3)
Classifier: Programming Language :: Python :: 3
Classifier: Programming Language :: Python :: 3.7
Classifier: Programming Language :: Python :: 3.8
Classifier: Programming Language :: Python :: 3.9
Classifier: Programming Language :: Python :: 3.10
Classifier: Programming Language :: Python :: 3.11
Requires-Dist: portablemc (>=3,<4)
Requires-Dist: prompt-toolkit (>=3.0.16,<3.1.0)
